computage/__init__.py
computage/settings.py
computage/analyzer/__init__.py
computage/analyzer/timecourse.py
computage/benchmarking/__init__.py
computage/benchmarking/benchmarking.py
computage/configs/__init__.py
computage/configs/datasets_bench_config.py
computage/configs/links_config.py
computage/configs/models_bench_config.py
computage/data_library/BenchBSB_table.csv
computage/data_library/__init__.py
computage/data_library/data_repository.py
computage/deage/__init__.py
computage/deage/automodel.py
computage/deage/base.py
computage/deage/kdm.py
computage/deage/pls.py
computage/models_library/__init__.py
computage/models_library/definitions.py
computage/models_library/model.py
computage/models_library/clocks/450K_reinius_12_reference.csv
computage/models_library/clocks/AD_Bahado-Singh.csv
computage/models_library/clocks/Alcohol.csv
computage/models_library/clocks/BMI.csv
computage/models_library/clocks/BMI_McCartney.csv
computage/models_library/clocks/BMI_Reed.csv
computage/models_library/clocks/BodyFatMcCartney.csv
computage/models_library/clocks/Bohlin.csv
computage/models_library/clocks/CVD_Westermann.csv
computage/models_library/clocks/DNAmClockCortical.csv
computage/models_library/clocks/DNAmTL.csv
computage/models_library/clocks/DepressionBarbu.csv
computage/models_library/clocks/DunedinPACE.csv
computage/models_library/clocks/DunedinPACE_Gold_Means.csv
computage/models_library/clocks/DunedinPoAm38.csv
computage/models_library/clocks/EPIC_salas_18_reference.csv
computage/models_library/clocks/EducationMcCartney.csv
computage/models_library/clocks/GrimAgeV1.csv
computage/models_library/clocks/GrimAgeV2.csv
computage/models_library/clocks/HDLCholesterolMcCartney.csv
computage/models_library/clocks/HRSInCHPhenoAge.csv
computage/models_library/clocks/Hannum.csv
computage/models_library/clocks/HepatoXu.csv
computage/models_library/clocks/Horvath1.csv
computage/models_library/clocks/Horvath2.csv
computage/models_library/clocks/Knight.csv
computage-0.1.7.dist-info/LICENSE
computage-0.1.7.dist-info/METADATA
computage-0.1.7.dist-info/WHEEL
computage-0.1.7.dist-info/top_level.txt
computage-0.1.7.dist-info/RECORD
