Metadata-Version: 2.2
Name: computage
Version: 0.1.7
Summary: A library for full-stack aging clocks design and benchmarking.
Author-email: dmitrii.kriukov@skoltech.ru
License-File: LICENSE
Requires-Dist: scikit-learn
Requires-Dist: scipy
Requires-Dist: statsmodels
Requires-Dist: pandas
Requires-Dist: numpy
Requires-Dist: tqdm
Requires-Dist: matplotlib
Requires-Dist: seaborn
Requires-Dist: huggingface_hub
Requires-Dist: pyarrow
Requires-Dist: fastparquet
Requires-Dist: plottable
Dynamic: author-email
Dynamic: requires-dist
Dynamic: summary
